LICENSE.txt
LinuxMemoryStatistics.py
MANIFEST.in
README.md
pyproject.toml
setup.cfg
setup.py
LinuxMemoryStatistics.egg-info/PKG-INFO
LinuxMemoryStatistics.egg-info/SOURCES.txt
LinuxMemoryStatistics.egg-info/dependency_links.txt
LinuxMemoryStatistics.egg-info/entry_points.txt
LinuxMemoryStatistics.egg-info/top_level.txt