Metadata-Version: 2.2
Name: LinuxMemoryStatistics
Version: 0.0.1
Summary: This script prints memory usages and statistics (by process, executable and for the full system).
Home-page: https://github.com/mauricelambert/LinuxMemoryStatistics
Download-URL: https://mauricelambert.github.io/info/python/code/LinuxMemoryStatistics.pyz
Author: Maurice Lambert
Author-email: Maurice Lambert <mauricelambert434@gmail.com>
Maintainer: Maurice Lambert
Maintainer-email: Maurice Lambert <mauricelambert434@gmail.com>
License: GPL-3.0 License
Project-URL: Github, https://github.com/mauricelambert/LinuxMemoryStatistics
Project-URL: Documentation, https://mauricelambert.github.io/info/python/code/LinuxMemoryStatistics.html
Project-URL: Python Executable, https://mauricelambert.github.io/info/python/code/LinuxMemoryStatistics.pyz
Project-URL: Windows Executable, https://mauricelambert.github.io/info/python/code/LinuxMemoryStatistics.exe
Keywords: memory,executable,process,system,linux,usages
Platform: Windows
Platform: Linux
Platform: MacOS
Classifier: Topic :: System
Classifier: Environment :: Console
Classifier: Topic :: System :: Shells
Classifier: Operating System :: POSIX
Classifier: Natural Language :: English
Classifier: Programming Language :: Python
Classifier: Topic :: System :: System Shells
Classifier: Programming Language :: Python :: 3.8
Classifier: Operating System :: Microsoft :: Windows
Classifier: Topic :: System :: Systems Administration
Classifier: Intended Audience :: System Administrators
Classifier: Development Status :: 5 - Production/Stable
Classifier: License :: OSI Approved :: GNU General Public License v3 or later (GPLv3+)
Requires-Python: >=3.8
License-File: LICENSE.txt
Dynamic: author
Dynamic: download-url
Dynamic: home-page
Dynamic: maintainer
Dynamic: requires-python
